dynasor/__init__.py
dynasor/correlation_functions.py
dynasor/logging_tools.py
dynasor/sample.py
dynasor/units.py
dynasor/cli/__init__.py
dynasor/cli/main.py
dynasor/core/__init__.py
dynasor/core/reciprocal.py
dynasor/core/rho_j_q_numba.py
dynasor/core/time_averager.py
dynasor/modes/__init__.py
dynasor/modes/atoms.py
dynasor/modes/band.py
dynasor/modes/complex_coordinate.py
dynasor/modes/mode_projector.py
dynasor/modes/project_modes.py
dynasor/modes/qpoint.py
dynasor/modes/tools.py
dynasor/post_processing/__init__.py
dynasor/post_processing/atomic_weighting.py
dynasor/post_processing/average_runs.py
dynasor/post_processing/electron_scattering_factors.py
dynasor/post_processing/filon.py
dynasor/post_processing/neutron_scattering_lengths.py
dynasor/post_processing/spherical_average.py
dynasor/post_processing/weights.py
dynasor/post_processing/x_ray_form_factors.py
dynasor/post_processing/form-factors/compton-parameters-waasmaier-kirfel-1995.json
dynasor/post_processing/form-factors/electron-parameters-ions-peng-1998.json
dynasor/post_processing/form-factors/electron-parameters-kmax2-peng-1996.json
dynasor/post_processing/form-factors/electron-parameters-kmax6-peng-1996.json
dynasor/post_processing/form-factors/neutron_scattering_lengths.json
dynasor/post_processing/form-factors/x-ray-parameters-itcc-2006.json
dynasor/post_processing/form-factors/x-ray-parameters-waasmaier-kirfel-1995.json
dynasor/qpoints/__init__.py
dynasor/qpoints/lattice.py
dynasor/qpoints/spherical_qpoints.py
dynasor/qpoints/tools.py
dynasor/tools/__init__.py
dynasor/tools/acfs.py
dynasor/tools/damped_harmonic_oscillator.py
dynasor/tools/structures.py
dynasor/trajectory/__init__.py
dynasor/trajectory/abstract_trajectory_reader.py
dynasor/trajectory/ase_trajectory_reader.py
dynasor/trajectory/atomic_indices.py
dynasor/trajectory/extxyz_trajectory_reader.py
dynasor/trajectory/lammps_trajectory_reader.py
dynasor/trajectory/mdanalysis_trajectory_reader.py
dynasor/trajectory/trajectory.py
dynasor-2.3.dist-info/licenses/LICENSE
dynasor-2.3.dist-info/METADATA
dynasor-2.3.dist-info/WHEEL
dynasor-2.3.dist-info/entry_points.txt
dynasor-2.3.dist-info/top_level.txt
dynasor-2.3.dist-info/RECORD
