Metadata-Version: 2.4
Name: dynasor
Version: 2.3
Summary: Dynamical structure factors and correlation functions from molecular dynamics trajectories
Author: The dynasor developer team
Maintainer: The dynasor developer team
License-Expression: MIT
Project-URL: Documentation, https://dynasor.materialsmodeling.org
Project-URL: Repository, https://gitlab.com/materials-modeling/dynasor/
Keywords: chemistry,physics,scientific
Classifier: Development Status :: 5 - Production/Stable
Classifier: Operating System :: OS Independent
Classifier: Programming Language :: Python :: 3 :: Only
Classifier: Programming Language :: Python :: 3
Classifier: Programming Language :: Python :: 3.9
Classifier: Programming Language :: Python :: 3.10
Classifier: Programming Language :: Python :: 3.11
Classifier: Programming Language :: Python :: 3.12
Classifier: Programming Language :: Python :: 3.13
Classifier: Intended Audience :: Education
Classifier: Intended Audience :: Science/Research
Classifier: Programming Language :: Python
Classifier: Topic :: Scientific/Engineering :: Chemistry
Classifier: Topic :: Scientific/Engineering :: Physics
Requires-Python: >=3.9
License-File: LICENSE
Requires-Dist: ase
Requires-Dist: mdanalysis
Requires-Dist: numba>=0.55
Requires-Dist: numpy>=1.18
Requires-Dist: pandas>=2.2
Requires-Dist: scipy
Provides-Extra: test
Requires-Dist: coverage; extra == "test"
Requires-Dist: flake8; extra == "test"
Requires-Dist: phonopy; extra == "test"
Requires-Dist: pytest; extra == "test"
Requires-Dist: xdoctest; extra == "test"
Provides-Extra: documentation
Requires-Dist: pydata-sphinx-theme; extra == "documentation"
Requires-Dist: nbsphinx; extra == "documentation"
Requires-Dist: sphinx-autodoc-typehints; extra == "documentation"
Requires-Dist: sphinx-design; extra == "documentation"
Requires-Dist: sphinx-sitemap; extra == "documentation"
Dynamic: license-file
